eduroam_config/__init__.py
eduroam_config/eduroam_service.py
eduroam_config/entry_point.py
eduroam_config/utils.py
eduroam_config/wpa_supplicant_config.py
eduroam_config/bin/_bz2.cpython-35m-arm-linux-gnueabihf.so
eduroam_config/bin/_codecs_cn.cpython-35m-arm-linux-gnueabihf.so
eduroam_config/bin/_codecs_hk.cpython-35m-arm-linux-gnueabihf.so
eduroam_config/bin/_codecs_iso2022.cpython-35m-arm-linux-gnueabihf.so
eduroam_config/bin/_codecs_jp.cpython-35m-arm-linux-gnueabihf.so
eduroam_config/bin/_codecs_kr.cpython-35m-arm-linux-gnueabihf.so
eduroam_config/bin/_codecs_tw.cpython-35m-arm-linux-gnueabihf.so
eduroam_config/bin/_ctypes.cpython-35m-arm-linux-gnueabihf.so
eduroam_config/bin/_dbm.cpython-35m-arm-linux-gnueabihf.so
eduroam_config/bin/_hashlib.cpython-35m-arm-linux-gnueabihf.so
eduroam_config/bin/_lzma.cpython-35m-arm-linux-gnueabihf.so
eduroam_config/bin/_multibytecodec.cpython-35m-arm-linux-gnueabihf.so
eduroam_config/bin/_opcode.cpython-35m-arm-linux-gnueabihf.so
eduroam_config/bin/_pytransform.so
eduroam_config/bin/_ssl.cpython-35m-arm-linux-gnueabihf.so
eduroam_config/bin/base_library.zip
eduroam_config/bin/libbz2.so.1.0
eduroam_config/bin/libcrypto.so.1.1
eduroam_config/bin/libdb-5.3.so
eduroam_config/bin/libexpat.so.1
eduroam_config/bin/libgcc_s.so.1
eduroam_config/bin/liblzma.so.5
eduroam_config/bin/libpython3.5m.so.1.0
eduroam_config/bin/libreadline.so.7
eduroam_config/bin/libssl.so.1.1
eduroam_config/bin/libtinfo.so.5
eduroam_config/bin/libz.so.1
eduroam_config/bin/license.lic
eduroam_config/bin/notify
eduroam_config/bin/pytransform.key
eduroam_config/bin/readline.cpython-35m-arm-linux-gnueabihf.so
eduroam_config/bin/resource.cpython-35m-arm-linux-gnueabihf.so
eduroam_config/bin/termios.cpython-35m-arm-linux-gnueabihf.so
eduroam_pi-0.7.0.dist-info/LICENSE
eduroam_pi-0.7.0.dist-info/METADATA
eduroam_pi-0.7.0.dist-info/WHEEL
eduroam_pi-0.7.0.dist-info/entry_points.txt
eduroam_pi-0.7.0.dist-info/top_level.txt
eduroam_pi-0.7.0.dist-info/RECORD
