Metadata-Version: 2.1
Name: eduroam-pi
Version: 0.7.0
Summary: Networking package to connect to enterprise eduroam and obtainIP for ssh connection.
Home-page: UNKNOWN
Author: Benjamin Ryan Daghir
Author-email: daghirb@gmail.com
License: UNKNOWN
Platform: UNKNOWN
Classifier: Programming Language :: Python :: 3
Classifier: License :: OSI Approved :: MIT License
Classifier: Operating System :: OS Independent
Requires-Python: >=3.5
